NEDAS/__init__.py
NEDAS/__main__.py
NEDAS/assim_tools/__init__.py
NEDAS/assim_tools/assimilators/__init__.py
NEDAS/assim_tools/assimilators/base.py
NEDAS/assim_tools/assimilators/batch.py
NEDAS/assim_tools/assimilators/get_assimilator.py
NEDAS/assim_tools/assimilators/serial.py
NEDAS/assim_tools/assimilators/EAKF/__init__.py
NEDAS/assim_tools/assimilators/EAKF/core.py
NEDAS/assim_tools/assimilators/ETKF/__init__.py
NEDAS/assim_tools/assimilators/ETKF/core.py
NEDAS/assim_tools/assimilators/TopazDEnKF/__init__.py
NEDAS/assim_tools/assimilators/TopazDEnKF/core.py
NEDAS/assim_tools/covariance/__init__.py
NEDAS/assim_tools/covariance/ensemble.py
NEDAS/assim_tools/covariance/get_covariance.py
NEDAS/assim_tools/covariance/static.py
NEDAS/assim_tools/inflation/RTPP.py
NEDAS/assim_tools/inflation/__init__.py
NEDAS/assim_tools/inflation/base.py
NEDAS/assim_tools/inflation/get_inflation_func.py
NEDAS/assim_tools/inflation/multiplicative.py
NEDAS/assim_tools/likelihood/normal.py
NEDAS/assim_tools/localization/__init__.py
NEDAS/assim_tools/localization/distance_based.py
NEDAS/assim_tools/localization/get_localization_funcs.py
NEDAS/assim_tools/obs/__init__.py
NEDAS/assim_tools/obs/base.py
NEDAS/assim_tools/obs/get_obs.py
NEDAS/assim_tools/state/__init__.py
NEDAS/assim_tools/state/base.py
NEDAS/assim_tools/state/get_state.py
NEDAS/assim_tools/transforms/__init__.py
NEDAS/assim_tools/transforms/base.py
NEDAS/assim_tools/transforms/get_transform_funcs.py
NEDAS/assim_tools/transforms/identity.py
NEDAS/assim_tools/transforms/scale_bandpass.py
NEDAS/assim_tools/updators/__init__.py
NEDAS/assim_tools/updators/additive.py
NEDAS/assim_tools/updators/alignment.py
NEDAS/assim_tools/updators/alignment_interp.py
NEDAS/assim_tools/updators/base.py
NEDAS/assim_tools/updators/get_updator.py
NEDAS/config/__init__.py
NEDAS/config/config.py
NEDAS/config/parse_config.py
NEDAS/datasets/__init__.py
NEDAS/datasets/base.py
NEDAS/datasets/get_dataset_class.py
NEDAS/datasets/cs2smos/__init__.py
nedas-1.1.0.dist-info/licenses/LICENSE
nedas-1.1.0.dist-info/METADATA
nedas-1.1.0.dist-info/WHEEL
nedas-1.1.0.dist-info/entry_points.txt
nedas-1.1.0.dist-info/top_level.txt
nedas-1.1.0.dist-info/RECORD
