Metadata-Version: 2.4
Name: NEDAS
Version: 1.1.0
Author-email: Yue Ying <yue.ying@nersc.no>
Project-URL: Homepage, https://github.com/nansencenter/NEDAS
Classifier: Programming Language :: Python :: 3
Classifier: License :: OSI Approved :: BSD License
Classifier: Operating System :: OS Independent
Requires-Python: >=3.8
License-File: LICENSE
Requires-Dist: numpy
Requires-Dist: scipy
Requires-Dist: matplotlib
Requires-Dist: pyproj
Requires-Dist: pyshp
Requires-Dist: netCDF4
Requires-Dist: PyYAML
Provides-Extra: all
Requires-Dist: mpi4py; extra == "all"
Requires-Dist: numba; extra == "all"
Requires-Dist: pyFFTW; extra == "all"
Requires-Dist: pygrib; extra == "all"
Requires-Dist: opencv; extra == "all"
Requires-Dist: tensorflow; extra == "all"
Requires-Dist: torch; extra == "all"
Provides-Extra: mpi
Requires-Dist: mpi4py; extra == "mpi"
Provides-Extra: jit
Requires-Dist: numba; extra == "jit"
Provides-Extra: fftw
Requires-Dist: pyFFTW; extra == "fftw"
Provides-Extra: grib
Requires-Dist: pygrib; extra == "grib"
Provides-Extra: alignment
Requires-Dist: opencv; extra == "alignment"
Provides-Extra: emulator
Requires-Dist: tensorflow; extra == "emulator"
Requires-Dist: torch; extra == "emulator"
Dynamic: license-file
